[
    {
        "name": "La première liste du kanban 1",
        "order": "1",
        "kanban_id": "1"
    },
    {
        "name": "La seconde liste du kanban 1",
        "order": "2",
        "kanban_id": "1"
    },
    {
        "name": "La troisième liste du kanban 1",
        "order": "3",
        "kanban_id": "1"
    },
    {
        "name": "La première liste du kanban 2",
        "order": "1",
        "kanban_id": "2"
    },
    {
        "name": "La seconde liste du kanban 2",
        "order": "2",
        "kanban_id": "2"
    },
    {
        "name": "La première liste du kanban 3",
        "order": "1",
        "kanban_id": "3"
    }

]